setup.py
django_webtemplates.egg-info/PKG-INFO
django_webtemplates.egg-info/SOURCES.txt
django_webtemplates.egg-info/dependency_links.txt
django_webtemplates.egg-info/requires.txt
django_webtemplates.egg-info/top_level.txt
webtemplates/__init__.py
webtemplates/loaders.py