Metadata-Version: 1.1
Name: django-webtemplates
Version: 0.1.2
Summary: Load templates from an external web site.
Home-page: https://bitbucket.org/ionata/django-webtemplates
Author: Tim Heap
Author-email: tim@ionata.com.au
License: UNKNOWN
Platform: UNKNOWN
Classifier: Environment :: Web Environment
Classifier: Intended Audience :: Developers
Classifier: Operating System :: OS Independent
Classifier: Programming Language :: Python
Classifier: Framework :: Django
